<?xml version="1.0"?>






































	<buses rt="171" rtRtpiFeedName="" rtdd="171"> <!-- @11 @16 -->

		<time>4:53 PM</time>


		<bus>
			<id>1192</id>    
			<consist></consist>    
			<cars></cars>    
			<rtpiFeedName></rtpiFeedName>
			<m>1</m>	  	
			<rt>171</rt>
			<rtRtpiFeedName></rtRtpiFeedName>
			<rtdd>171</rtdd>  
			
			<d>East Bound</d>
			<dd>Northbound</dd> 
			<dn>ENE</dn> 
			<lat>41.79961013793945</lat>
			<lon>-87.58373641967773</lon>
			<pid>14111</pid>
			<pd>Northbound</pd> 
			<pdRtpiFeedName></pdRtpiFeedName>
			<run>1703</run>
			<fs>South Shore/54th</fs>
			<op>52792</op>
			<dip>12522</dip>
			<bid>1236</bid>				
			<wid1>01</wid1>
			<wid2>703</wid2>            	
		</bus>



	</buses>
