<?xml version="1.0"?>






































	<buses rt="75" rtRtpiFeedName="" rtdd="75"> <!-- @11 @16 -->

		<time>5:30 PM</time>


		<bus>
			<id>1469</id>    
			<consist></consist>    
			<cars></cars>    
			<rtpiFeedName></rtpiFeedName>
			<m>1</m>	  	
			<rt>75</rt>
			<rtRtpiFeedName></rtRtpiFeedName>
			<rtdd>75</rtdd>  
			
			<d>East Bound</d>
			<dd>Eastbound</dd> 
			<dn>E</dn> 
			<lat>41.75809860229492</lat>
			<lon>-87.63224146916316</lon>
			<pid>1540</pid>
			<pd>Eastbound</pd> 
			<pdRtpiFeedName></pdRtpiFeedName>
			<run>6575</run>
			<fs>Lakefront</fs>
			<op>61846</op>
			<dip>14546</dip>
			<bid>2545</bid>				
			<wid1>06</wid1>
			<wid2>575</wid2>            	
		</bus>



		<bus>
			<id>1464</id>    
			<consist></consist>    
			<cars></cars>    
			<rtpiFeedName></rtpiFeedName>
			<m>1</m>	  	
			<rt>75</rt>
			<rtRtpiFeedName></rtRtpiFeedName>
			<rtdd>75</rtdd>  
			
			<d>West Bound</d>
			<dd>Westbound</dd> 
			<dn>W</dn> 
			<lat>41.75834854443868</lat>
			<lon>-87.61835527420044</lon>
			<pid>1541</pid>
			<pd>Westbound</pd> 
			<pdRtpiFeedName></pdRtpiFeedName>
			<run>6579</run>
			<fs>Damen</fs>
			<op>59673</op>
			<dip>17670</dip>
			<bid>2573</bid>				
			<wid1>06</wid1>
			<wid2>579</wid2>            	
		</bus>



		<bus>
			<id>1465</id>    
			<consist></consist>    
			<cars></cars>    
			<rtpiFeedName></rtpiFeedName>
			<m>1</m>	  	
			<rt>75</rt>
			<rtRtpiFeedName></rtRtpiFeedName>
			<rtdd>75</rtdd>  
			
			<d>North East Bound</d>
			<dd>Eastbound</dd> 
			<dn>ENE</dn> 
			<lat>41.750975623497595</lat>
			<lon>-87.62548112135667</lon>
			<pid>1540</pid>
			<pd>Eastbound</pd> 
			<pdRtpiFeedName></pdRtpiFeedName>
			<run>6583</run>
			<fs>Lakefront</fs>
			<op>66353</op>
			<dip>18821</dip>
			<bid>2586</bid>				
			<wid1>06</wid1>
			<wid2>583</wid2>            	
		</bus>



		<bus>
			<id>1504</id>    
			<consist></consist>    
			<cars></cars>    
			<rtpiFeedName></rtpiFeedName>
			<m>1</m>	  	
			<rt>75</rt>
			<rtRtpiFeedName></rtRtpiFeedName>
			<rtdd>75</rtdd>  
			
			<d>West Bound</d>
			<dd>Westbound</dd> 
			<dn>W</dn> 
			<lat>41.75818021369703</lat>
			<lon>-87.63105068784772</lon>
			<pid>1541</pid>
			<pd>Westbound</pd> 
			<pdRtpiFeedName></pdRtpiFeedName>
			<run>6572</run>
			<fs>Damen</fs>
			<op>53985</op>
			<dip>27361</dip>
			<bid>2575</bid>				
			<wid1>06</wid1>
			<wid2>572</wid2>            	
		</bus>



		<bus>
			<id>1425</id>    
			<consist></consist>    
			<cars></cars>    
			<rtpiFeedName></rtpiFeedName>
			<m>1</m>	  	
			<rt>75</rt>
			<rtRtpiFeedName></rtRtpiFeedName>
			<rtdd>75</rtdd>  
			
			<d>East Bound</d>
			<dd>Eastbound</dd> 
			<dn>E</dn> 
			<lat>41.75886223532937</lat>
			<lon>-87.57628492875533</lon>
			<pid>1540</pid>
			<pd>Eastbound</pd> 
			<pdRtpiFeedName></pdRtpiFeedName>
			<run>6574</run>
			<fs>Lakefront</fs>
			<op>61838</op>
			<dip>34981</dip>
			<bid>2842</bid>				
			<wid1>06</wid1>
			<wid2>574</wid2>            	
		</bus>



	</buses>
