<?xml version="1.0"?>






































	<buses rt="15" rtRtpiFeedName="" rtdd="15"> <!-- @11 @16 -->

		<time>1:14 PM</time>


		<bus>
			<id>1067</id>    
			<consist></consist>    
			<cars></cars>    
			<rtpiFeedName></rtpiFeedName>
			<m>1</m>	  	
			<rt>15</rt>
			<rtRtpiFeedName></rtRtpiFeedName>
			<rtdd>15</rtdd>  
			
			<d>South East Bound</d>
			<dd>Northbound</dd> 
			<dn>SSE</dn> 
			<lat>41.708553314208984</lat>
			<lon>-87.58123016357422</lon>
			<pid>4288</pid>
			<pd>Northbound</pd> 
			<pdRtpiFeedName></pdRtpiFeedName>
			<run>1418</run>
			<fs>47th Red Line</fs>
			<op>37090</op>
			<dip>0</dip>
			<bid>1228</bid>				
			<wid1>01</wid1>
			<wid2>418</wid2>            	
		</bus>



		<bus>
			<id>1106</id>    
			<consist></consist>    
			<cars></cars>    
			<rtpiFeedName></rtpiFeedName>
			<m>1</m>	  	
			<rt>15</rt>
			<rtRtpiFeedName></rtRtpiFeedName>
			<rtdd>15</rtdd>  
			
			<d>West Bound</d>
			<dd>Southbound</dd> 
			<dn>W</dn> 
			<lat>41.809173583984375</lat>
			<lon>-87.63185119628906</lon>
			<pid>4287</pid>
			<pd>Southbound</pd> 
			<pdRtpiFeedName></pdRtpiFeedName>
			<run>1473</run>
			<fs>Stony Island/103rd</fs>
			<op>49757</op>
			<dip>47</dip>
			<bid>1092</bid>				
			<wid1>01</wid1>
			<wid2>473</wid2>            	
		</bus>



		<bus>
			<id>1121</id>    
			<consist></consist>    
			<cars></cars>    
			<rtpiFeedName></rtpiFeedName>
			<m>1</m>	  	
			<rt>15</rt>
			<rtRtpiFeedName></rtRtpiFeedName>
			<rtdd>15</rtdd>  
			
			<d>East Bound</d>
			<dd>Southbound</dd> 
			<dn>ENE</dn> 
			<lat>41.80215835571289</lat>
			<lon>-87.60348510742188</lon>
			<pid>4287</pid>
			<pd>Southbound</pd> 
			<pdRtpiFeedName></pdRtpiFeedName>
			<run>1408</run>
			<fs>Stony Island/103rd</fs>
			<op>N/A</op>
			<dip>10860</dip>
			<bid>1091</bid>				
			<wid1>01</wid1>
			<wid2>408</wid2>            	
		</bus>



		<bus>
			<id>8339</id>    
			<consist></consist>    
			<cars></cars>    
			<rtpiFeedName></rtpiFeedName>
			<m>1</m>	  	
			<rt>15</rt>
			<rtRtpiFeedName></rtRtpiFeedName>
			<rtdd>15</rtdd>  
			
			<d>North Bound</d>
			<dd>Northbound</dd> 
			<dn>N</dn> 
			<lat>41.748429489135745</lat>
			<lon>-87.57587432861328</lon>
			<pid>4288</pid>
			<pd>Northbound</pd> 
			<pdRtpiFeedName></pdRtpiFeedName>
			<run>1415</run>
			<fs>47th Red Line</fs>
			<op>37094</op>
			<dip>21993</dip>
			<bid>1094</bid>				
			<wid1>01</wid1>
			<wid2>415</wid2>            	
		</bus>



		<bus>
			<id>1127</id>    
			<consist></consist>    
			<cars></cars>    
			<rtpiFeedName></rtpiFeedName>
			<m>1</m>	  	
			<rt>15</rt>
			<rtRtpiFeedName></rtRtpiFeedName>
			<rtdd>15</rtdd>  
			
			<d>East Bound</d>
			<dd>Southbound</dd> 
			<dn>E</dn> 
			<lat>41.773356360358164</lat>
			<lon>-87.58443347827809</lon>
			<pid>4287</pid>
			<pd>Southbound</pd> 
			<pdRtpiFeedName></pdRtpiFeedName>
			<run>1433</run>
			<fs>Stony Island/103rd</fs>
			<op>52482</op>
			<dip>26781</dip>
			<bid>1096</bid>				
			<wid1>01</wid1>
			<wid2>433</wid2>            	
		</bus>



		<bus>
			<id>1089</id>    
			<consist></consist>    
			<cars></cars>    
			<rtpiFeedName></rtpiFeedName>
			<m>1</m>	  	
			<rt>15</rt>
			<rtRtpiFeedName></rtRtpiFeedName>
			<rtdd>15</rtdd>  
			
			<d>South Bound</d>
			<dd>Southbound</dd> 
			<dn>S</dn> 
			<lat>41.767448038294695</lat>
			<lon>-87.57628089794214</lon>
			<pid>4287</pid>
			<pd>Southbound</pd> 
			<pdRtpiFeedName></pdRtpiFeedName>
			<run>1406</run>
			<fs>Stony Island/103rd</fs>
			<op>34236</op>
			<dip>31260</dip>
			<bid>1090</bid>				
			<wid1>01</wid1>
			<wid2>406</wid2>            	
		</bus>



		<bus>
			<id>8335</id>    
			<consist></consist>    
			<cars></cars>    
			<rtpiFeedName></rtpiFeedName>
			<m>1</m>	  	
			<rt>15</rt>
			<rtRtpiFeedName></rtRtpiFeedName>
			<rtdd>15</rtdd>  
			
			<d>North Bound</d>
			<dd>Northbound</dd> 
			<dn>NNW</dn> 
			<lat>41.79125213623047</lat>
			<lon>-87.58661651611328</lon>
			<pid>4288</pid>
			<pd>Northbound</pd> 
			<pdRtpiFeedName></pdRtpiFeedName>
			<run>1471</run>
			<fs>47th Red Line</fs>
			<op>34234</op>
			<dip>40966</dip>
			<bid>1093</bid>				
			<wid1>01</wid1>
			<wid2>471</wid2>            	
		</bus>



		<bus>
			<id>1095</id>    
			<consist></consist>    
			<cars></cars>    
			<rtpiFeedName></rtpiFeedName>
			<m>1</m>	  	
			<rt>15</rt>
			<rtRtpiFeedName></rtRtpiFeedName>
			<rtdd>15</rtdd>  
			
			<d>West Bound</d>
			<dd>Northbound</dd> 
			<dn>W</dn> 
			<lat>41.802253222856365</lat>
			<lon>-87.60718561391361</lon>
			<pid>4288</pid>
			<pd>Northbound</pd> 
			<pdRtpiFeedName></pdRtpiFeedName>
			<run>1413</run>
			<fs>47th Red Line</fs>
			<op>45356</op>
			<dip>50944</dip>
			<bid>1323</bid>				
			<wid1>01</wid1>
			<wid2>413</wid2>            	
		</bus>



	</buses>
