<?xml version="1.0"?>






































	<buses rt="35" rtRtpiFeedName="" rtdd="35"> <!-- @11 @16 -->

		<time>4:53 PM</time>


		<bus>
			<id>7908</id>    
			<consist></consist>    
			<cars></cars>    
			<rtpiFeedName></rtpiFeedName>
			<m>1</m>	  	
			<rt>35</rt>
			<rtRtpiFeedName></rtRtpiFeedName>
			<rtdd>35</rtdd>  
			
			<d>East Bound</d>
			<dd>Eastbound</dd> 
			<dn>E</dn> 
			<lat>41.836788642697215</lat>
			<lon>-87.731632697873</lon>
			<pid>14102</pid>
			<pd>Eastbound</pd> 
			<pdRtpiFeedName></pdRtpiFeedName>
			<run>K309</run>
			<fs>31st Street Beach</fs>
			<op>54101</op>
			<dip>7425</dip>
			<bid>1750</bid>				
			<wid1>0K</wid1>
			<wid2>309</wid2>            	
		</bus>



		<bus>
			<id>1656</id>    
			<consist></consist>    
			<cars></cars>    
			<rtpiFeedName></rtpiFeedName>
			<m>1</m>	  	
			<rt>35</rt>
			<rtRtpiFeedName></rtRtpiFeedName>
			<rtdd>35</rtdd>  
			
			<d>West Bound</d>
			<dd>Westbound</dd> 
			<dn>W</dn> 
			<lat>41.831031799316406</lat>
			<lon>-87.6302490234375</lon>
			<pid>7205</pid>
			<pd>Westbound</pd> 
			<pdRtpiFeedName></pdRtpiFeedName>
			<run>K312</run>
			<fs>24th Pl/Cicero</fs>
			<op>62087</op>
			<dip>12036</dip>
			<bid>1765</bid>				
			<wid1>0K</wid1>
			<wid2>312</wid2>            	
		</bus>



		<bus>
			<id>1669</id>    
			<consist></consist>    
			<cars></cars>    
			<rtpiFeedName></rtpiFeedName>
			<m>1</m>	  	
			<rt>35</rt>
			<rtRtpiFeedName></rtRtpiFeedName>
			<rtdd>35</rtdd>  
			
			<d>East Bound</d>
			<dd>Eastbound</dd> 
			<dn>E</dn> 
			<lat>41.828102111816406</lat>
			<lon>-87.70301055908203</lon>
			<pid>14102</pid>
			<pd>Eastbound</pd> 
			<pdRtpiFeedName></pdRtpiFeedName>
			<run>K317</run>
			<fs>31st Street Beach</fs>
			<op>52813</op>
			<dip>19012</dip>
			<bid>1755</bid>				
			<wid1>0K</wid1>
			<wid2>317</wid2>            	
		</bus>



		<bus>
			<id>1007</id>    
			<consist></consist>    
			<cars></cars>    
			<rtpiFeedName></rtpiFeedName>
			<m>1</m>	  	
			<rt>35</rt>
			<rtRtpiFeedName></rtRtpiFeedName>
			<rtdd>35</rtdd>  
			
			<d>East Bound</d>
			<dd>Eastbound</dd> 
			<dn>E</dn> 
			<lat>41.830495107741584</lat>
			<lon>-87.66589973086403</lon>
			<pid>14102</pid>
			<pd>Eastbound</pd> 
			<pdRtpiFeedName></pdRtpiFeedName>
			<run>K316</run>
			<fs>31st Street Beach</fs>
			<op>53982</op>
			<dip>31390</dip>
			<bid>1762</bid>				
			<wid1>0K</wid1>
			<wid2>316</wid2>            	
		</bus>



		<bus>
			<id>1689</id>    
			<consist></consist>    
			<cars></cars>    
			<rtpiFeedName></rtpiFeedName>
			<m>1</m>	  	
			<rt>35</rt>
			<rtRtpiFeedName></rtRtpiFeedName>
			<rtdd>35</rtdd>  
			
			<d>South Bound</d>
			<dd>Westbound</dd> 
			<dn>S</dn> 
			<lat>41.828870137532554</lat>
			<lon>-87.69487762451172</lon>
			<pid>7205</pid>
			<pd>Westbound</pd> 
			<pdRtpiFeedName></pdRtpiFeedName>
			<run>K319</run>
			<fs>24th Pl/Cicero</fs>
			<op>49692</op>
			<dip>31808</dip>
			<bid>1756</bid>				
			<wid1>0K</wid1>
			<wid2>319</wid2>            	
		</bus>



		<bus>
			<id>8106</id>    
			<consist></consist>    
			<cars></cars>    
			<rtpiFeedName></rtpiFeedName>
			<m>1</m>	  	
			<rt>35</rt>
			<rtRtpiFeedName></rtRtpiFeedName>
			<rtdd>35</rtdd>  
			
			<d>West Bound</d>
			<dd>Westbound</dd> 
			<dn>W</dn> 
			<lat>41.837210464477536</lat>
			<lon>-87.7097183227539</lon>
			<pid>7205</pid>
			<pd>Westbound</pd> 
			<pdRtpiFeedName></pdRtpiFeedName>
			<run>K306</run>
			<fs>24th Pl/Cicero</fs>
			<op>44907</op>
			<dip>39988</dip>
			<bid>1764</bid>				
			<wid1>0K</wid1>
			<wid2>306</wid2>            	
		</bus>



		<bus>
			<id>1736</id>    
			<consist></consist>    
			<cars></cars>    
			<rtpiFeedName></rtpiFeedName>
			<m>1</m>	  	
			<rt>35</rt>
			<rtRtpiFeedName></rtRtpiFeedName>
			<rtdd>35</rtdd>  
			
			<d>East Bound</d>
			<dd>Eastbound</dd> 
			<dn>E</dn> 
			<lat>41.831050872802734</lat>
			<lon>-87.62118032027264</lon>
			<pid>14102</pid>
			<pd>Eastbound</pd> 
			<pdRtpiFeedName></pdRtpiFeedName>
			<run>K315</run>
			<fs>31st Street Beach</fs>
			<op>50794</op>
			<dip>43584</dip>
			<bid>1754</bid>				
			<wid1>0K</wid1>
			<wid2>315</wid2>            	
		</bus>



		<bus>
			<id>1924</id>    
			<consist></consist>    
			<cars></cars>    
			<rtpiFeedName></rtpiFeedName>
			<m>1</m>	  	
			<rt>35</rt>
			<rtRtpiFeedName></rtRtpiFeedName>
			<rtdd>35</rtdd>  
			
			<d>North Bound</d>
			<dd>Eastbound</dd> 
			<dn>N</dn> 
			<lat>41.838319878829154</lat>
			<lon>-87.61348724365234</lon>
			<pid>14102</pid>
			<pd>Eastbound</pd> 
			<pdRtpiFeedName></pdRtpiFeedName>
			<run>K314</run>
			<fs>31st Street Beach</fs>
			<op>55788</op>
			<dip>48678</dip>
			<bid>1751</bid>				
			<wid1>0K</wid1>
			<wid2>314</wid2>            	
		</bus>



		<bus>
			<id>7906</id>    
			<consist></consist>    
			<cars></cars>    
			<rtpiFeedName></rtpiFeedName>
			<m>1</m>	  	
			<rt>35</rt>
			<rtRtpiFeedName></rtRtpiFeedName>
			<rtdd>35</rtdd>  
			
			<d>West Bound</d>
			<dd>Westbound</dd> 
			<dn>W</dn> 
			<lat>41.846595764160156</lat>
			<lon>-87.74447631835938</lon>
			<pid>7205</pid>
			<pd>Westbound</pd> 
			<pdRtpiFeedName></pdRtpiFeedName>
			<run>K320</run>
			<fs>24th Pl/Cicero</fs>
			<op>50036</op>
			<dip>52706</dip>
			<bid>1763</bid>				
			<wid1>0K</wid1>
			<wid2>320</wid2>            	
		</bus>



	</buses>
