<?xml version="1.0"?>






































	<buses rt="29" rtRtpiFeedName="" rtdd="29"> <!-- @11 @16 -->

		<time>4:49 PM</time>


		<bus>
			<id>1159</id>    
			<consist></consist>    
			<cars></cars>    
			<rtpiFeedName></rtpiFeedName>
			<m>1</m>	  	
			<rt>29</rt>
			<rtRtpiFeedName></rtRtpiFeedName>
			<rtdd>29</rtdd>  
			
			<d>South Bound</d>
			<dd>Southbound</dd> 
			<dn>S</dn> 
			<lat>41.88567848205567</lat>
			<lon>-87.62803649902344</lon>
			<pid>1042</pid>
			<pd>Southbound</pd> 
			<pdRtpiFeedName></pdRtpiFeedName>
			<run>1762</run>
			<fs>95th Red Line</fs>
			<op>64983</op>
			<dip>7505</dip>
			<bid>2</bid>				
			<wid1>01</wid1>
			<wid2>762</wid2>            	
		</bus>



		<bus>
			<id>1169</id>    
			<consist></consist>    
			<cars></cars>    
			<rtpiFeedName></rtpiFeedName>
			<m>1</m>	  	
			<rt>29</rt>
			<rtRtpiFeedName></rtRtpiFeedName>
			<rtdd>29</rtdd>  
			
			<d>North Bound</d>
			<dd>Northbound</dd> 
			<dn>N</dn> 
			<lat>41.80933423312205</lat>
			<lon>-87.62600362525797</lon>
			<pid>1039</pid>
			<pd>Northbound</pd> 
			<pdRtpiFeedName></pdRtpiFeedName>
			<run>1319</run>
			<fs>Navy Pier</fs>
			<op>66000</op>
			<dip>32039</dip>
			<bid>52</bid>				
			<wid1>01</wid1>
			<wid2>319</wid2>            	
		</bus>



		<bus>
			<id>1129</id>    
			<consist></consist>    
			<cars></cars>    
			<rtpiFeedName></rtpiFeedName>
			<m>1</m>	  	
			<rt>29</rt>
			<rtRtpiFeedName></rtRtpiFeedName>
			<rtdd>29</rtdd>  
			
			<d>North Bound</d>
			<dd>Northbound</dd> 
			<dn>N</dn> 
			<lat>41.82347687431004</lat>
			<lon>-87.6263198852539</lon>
			<pid>1039</pid>
			<pd>Northbound</pd> 
			<pdRtpiFeedName></pdRtpiFeedName>
			<run>1504</run>
			<fs>Navy Pier</fs>
			<op>58133</op>
			<dip>37196</dip>
			<bid>110</bid>				
			<wid1>01</wid1>
			<wid2>504</wid2>            	
		</bus>



		<bus>
			<id>1202</id>    
			<consist></consist>    
			<cars></cars>    
			<rtpiFeedName></rtpiFeedName>
			<m>1</m>	  	
			<rt>29</rt>
			<rtRtpiFeedName></rtRtpiFeedName>
			<rtdd>29</rtdd>  
			
			<d>South Bound</d>
			<dd>Southbound</dd> 
			<dn>S</dn> 
			<lat>41.787635273403595</lat>
			<lon>-87.6256103515625</lon>
			<pid>1042</pid>
			<pd>Southbound</pd> 
			<pdRtpiFeedName></pdRtpiFeedName>
			<run>1916</run>
			<fs>95th Red Line</fs>
			<op>65308</op>
			<dip>43498</dip>
			<bid>47</bid>				
			<wid1>01</wid1>
			<wid2>916</wid2>            	
		</bus>



		<bus>
			<id>8341</id>    
			<consist></consist>    
			<cars></cars>    
			<rtpiFeedName></rtpiFeedName>
			<m>1</m>	  	
			<rt>29</rt>
			<rtRtpiFeedName></rtRtpiFeedName>
			<rtdd>29</rtdd>  
			
			<d>North Bound</d>
			<dd>Northbound</dd> 
			<dn>N</dn> 
			<lat>41.88622908158736</lat>
			<lon>-87.62787628173828</lon>
			<pid>1039</pid>
			<pd>Northbound</pd> 
			<pdRtpiFeedName></pdRtpiFeedName>
			<run>1624</run>
			<fs>Navy Pier</fs>
			<op>65810</op>
			<dip>60188</dip>
			<bid>51</bid>				
			<wid1>01</wid1>
			<wid2>624</wid2>            	
		</bus>



		<bus>
			<id>1182</id>    
			<consist></consist>    
			<cars></cars>    
			<rtpiFeedName></rtpiFeedName>
			<m>1</m>	  	
			<rt>29</rt>
			<rtRtpiFeedName></rtRtpiFeedName>
			<rtdd>29</rtdd>  
			
			<d>East Bound</d>
			<dd>Northbound</dd> 
			<dn>E</dn> 
			<lat>41.89090392703102</lat>
			<lon>-87.62446975708008</lon>
			<pid>1039</pid>
			<pd>Northbound</pd> 
			<pdRtpiFeedName></pdRtpiFeedName>
			<run>1273</run>
			<fs>Navy Pier</fs>
			<op>51978</op>
			<dip>62822</dip>
			<bid>45</bid>				
			<wid1>01</wid1>
			<wid2>273</wid2>            	
		</bus>



	</buses>
