<?xml version="1.0"?>






































	<buses rt="20" rtRtpiFeedName="" rtdd="20"> <!-- @11 @16 -->

		<time>11:42 AM</time>


		<bus>
			<id>8159</id>    
			<consist></consist>    
			<cars></cars>    
			<rtpiFeedName></rtpiFeedName>
			<m>1</m>	  	
			<rt>20</rt>
			<rtRtpiFeedName></rtRtpiFeedName>
			<rtdd>20</rtdd>  
			
			<d>West Bound</d>
			<dd>Westbound</dd> 
			<dn>W</dn> 
			<lat>41.88196244110932</lat>
			<lon>-87.63294797330289</lon>
			<pid>954</pid>
			<pd>Westbound</pd> 
			<pdRtpiFeedName></pdRtpiFeedName>
			<run>5004</run>
			<fs>Austin</fs>
			<op>43332</op>
			<dip>2261</dip>
			<bid>1582</bid>				
			<wid1>05</wid1>
			<wid2>004</wid2>            	
		</bus>



		<bus>
			<id>8131</id>    
			<consist></consist>    
			<cars></cars>    
			<rtpiFeedName></rtpiFeedName>
			<m>1</m>	  	
			<rt>20</rt>
			<rtRtpiFeedName></rtRtpiFeedName>
			<rtdd>20</rtdd>  
			
			<d>East Bound</d>
			<dd>Eastbound</dd> 
			<dn>E</dn> 
			<lat>41.88018396165636</lat>
			<lon>-87.76526599460178</lon>
			<pid>956</pid>
			<pd>Eastbound</pd> 
			<pdRtpiFeedName></pdRtpiFeedName>
			<run>MAN</run>
			<fs>Pulaski</fs>
			<op>51895</op>
			<dip>2534</dip>
			<bid>MAN</bid>				
			<wid1>05</wid1>
			<wid2>008</wid2>            	
		</bus>



		<bus>
			<id>1952</id>    
			<consist></consist>    
			<cars></cars>    
			<rtpiFeedName></rtpiFeedName>
			<m>1</m>	  	
			<rt>20</rt>
			<rtRtpiFeedName></rtRtpiFeedName>
			<rtdd>20</rtdd>  
			
			<d>West Bound</d>
			<dd>Westbound</dd> 
			<dn>W</dn> 
			<lat>41.88144302368164</lat>
			<lon>-87.66925430297852</lon>
			<pid>954</pid>
			<pd>Westbound</pd> 
			<pdRtpiFeedName></pdRtpiFeedName>
			<run>5003</run>
			<fs>Austin</fs>
			<op>40399</op>
			<dip>12248</dip>
			<bid>1368</bid>				
			<wid1>05</wid1>
			<wid2>003</wid2>            	
		</bus>



		<bus>
			<id>8170</id>    
			<consist></consist>    
			<cars></cars>    
			<rtpiFeedName></rtpiFeedName>
			<m>1</m>	  	
			<rt>20</rt>
			<rtRtpiFeedName></rtRtpiFeedName>
			<rtdd>20</rtdd>  
			
			<d>East Bound</d>
			<dd>Eastbound</dd> 
			<dn>E</dn> 
			<lat>41.88077659606934</lat>
			<lon>-87.72107162475587</lon>
			<pid>957</pid>
			<pd>Eastbound</pd> 
			<pdRtpiFeedName></pdRtpiFeedName>
			<run>5002</run>
			<fs>Michigan</fs>
			<op>40981</op>
			<dip>14836</dip>
			<bid>1370</bid>				
			<wid1>05</wid1>
			<wid2>002</wid2>            	
		</bus>



		<bus>
			<id>1964</id>    
			<consist></consist>    
			<cars></cars>    
			<rtpiFeedName></rtpiFeedName>
			<m>1</m>	  	
			<rt>20</rt>
			<rtRtpiFeedName></rtRtpiFeedName>
			<rtdd>20</rtdd>  
			
			<d>East Bound</d>
			<dd>Eastbound</dd> 
			<dn>E</dn> 
			<lat>41.880802154541016</lat>
			<lon>-87.72005775996617</lon>
			<pid>957</pid>
			<pd>Eastbound</pd> 
			<pdRtpiFeedName></pdRtpiFeedName>
			<run>5001</run>
			<fs>Michigan</fs>
			<op>40369</op>
			<dip>15118</dip>
			<bid>1367</bid>				
			<wid1>05</wid1>
			<wid2>001</wid2>            	
		</bus>



		<bus>
			<id>8150</id>    
			<consist></consist>    
			<cars></cars>    
			<rtpiFeedName></rtpiFeedName>
			<m>1</m>	  	
			<rt>20</rt>
			<rtRtpiFeedName></rtRtpiFeedName>
			<rtdd>20</rtdd>  
			
			<d>West Bound</d>
			<dd>Westbound</dd> 
			<dn>W</dn> 
			<lat>41.88101969824897</lat>
			<lon>-87.70033677419026</lon>
			<pid>954</pid>
			<pd>Westbound</pd> 
			<pdRtpiFeedName></pdRtpiFeedName>
			<run>5005</run>
			<fs>Austin</fs>
			<op>45065</op>
			<dip>20768</dip>
			<bid>1365</bid>				
			<wid1>05</wid1>
			<wid2>005</wid2>            	
		</bus>



		<bus>
			<id>8183</id>    
			<consist></consist>    
			<cars></cars>    
			<rtpiFeedName></rtpiFeedName>
			<m>1</m>	  	
			<rt>20</rt>
			<rtRtpiFeedName></rtRtpiFeedName>
			<rtdd>20</rtdd>  
			
			<d>East Bound</d>
			<dd>Eastbound</dd> 
			<dn>E</dn> 
			<lat>41.881431579589844</lat>
			<lon>-87.6681418785682</lon>
			<pid>957</pid>
			<pd>Eastbound</pd> 
			<pdRtpiFeedName></pdRtpiFeedName>
			<run>5006</run>
			<fs>Michigan</fs>
			<op>31261</op>
			<dip>29687</dip>
			<bid>1579</bid>				
			<wid1>05</wid1>
			<wid2>006</wid2>            	
		</bus>



		<bus>
			<id>1955</id>    
			<consist></consist>    
			<cars></cars>    
			<rtpiFeedName></rtpiFeedName>
			<m>1</m>	  	
			<rt>20</rt>
			<rtRtpiFeedName></rtRtpiFeedName>
			<rtdd>20</rtdd>  
			
			<d>West Bound</d>
			<dd>Westbound</dd> 
			<dn>W</dn> 
			<lat>41.8806997763144</lat>
			<lon>-87.73361041094806</lon>
			<pid>954</pid>
			<pd>Westbound</pd> 
			<pdRtpiFeedName></pdRtpiFeedName>
			<run>5022</run>
			<fs>Austin</fs>
			<op>57759</op>
			<dip>29902</dip>
			<bid>1583</bid>				
			<wid1>05</wid1>
			<wid2>022</wid2>            	
		</bus>



		<bus>
			<id>2021</id>    
			<consist></consist>    
			<cars></cars>    
			<rtpiFeedName></rtpiFeedName>
			<m>1</m>	  	
			<rt>20</rt>
			<rtRtpiFeedName></rtRtpiFeedName>
			<rtdd>20</rtdd>  
			
			<d>West Bound</d>
			<dd>Westbound</dd> 
			<dn>W</dn> 
			<lat>41.88039171897759</lat>
			<lon>-87.75806465795485</lon>
			<pid>954</pid>
			<pd>Westbound</pd> 
			<pdRtpiFeedName></pdRtpiFeedName>
			<run>5023</run>
			<fs>Austin</fs>
			<op>58140</op>
			<dip>36581</dip>
			<bid>1625</bid>				
			<wid1>05</wid1>
			<wid2>023</wid2>            	
		</bus>



		<bus>
			<id>2024</id>    
			<consist></consist>    
			<cars></cars>    
			<rtpiFeedName></rtpiFeedName>
			<m>1</m>	  	
			<rt>20</rt>
			<rtRtpiFeedName></rtRtpiFeedName>
			<rtdd>20</rtdd>  
			
			<d>East Bound</d>
			<dd>Eastbound</dd> 
			<dn>E</dn> 
			<lat>41.883174896240234</lat>
			<lon>-87.63091278076172</lon>
			<pid>957</pid>
			<pd>Eastbound</pd> 
			<pdRtpiFeedName></pdRtpiFeedName>
			<run>5007</run>
			<fs>Michigan</fs>
			<op>42900</op>
			<dip>40489</dip>
			<bid>1546</bid>				
			<wid1>05</wid1>
			<wid2>007</wid2>            	
		</bus>



		<bus>
			<id>2018</id>    
			<consist></consist>    
			<cars></cars>    
			<rtpiFeedName></rtpiFeedName>
			<m>1</m>	  	
			<rt>20</rt>
			<rtRtpiFeedName></rtRtpiFeedName>
			<rtdd>20</rtdd>  
			
			<d>West Bound</d>
			<dd>Eastbound</dd> 
			<dn>W</dn> 
			<lat>41.882155418395996</lat>
			<lon>-87.62458419799805</lon>
			<pid>957</pid>
			<pd>Eastbound</pd> 
			<pdRtpiFeedName></pdRtpiFeedName>
			<run>5020</run>
			<fs>Michigan</fs>
			<op>53153</op>
			<dip>42601</dip>
			<bid>1577</bid>				
			<wid1>05</wid1>
			<wid2>020</wid2>            	
		</bus>



	</buses>
