<?xml version="1.0"?>






































	<buses rt="81" rtRtpiFeedName="" rtdd="81"> <!-- @11 @16 -->

		<time>9:44 PM</time>


		<bus>
			<id>1557</id>    
			<consist></consist>    
			<cars></cars>    
			<rtpiFeedName></rtpiFeedName>
			<m>1</m>	  	
			<rt>81</rt>
			<rtRtpiFeedName></rtRtpiFeedName>
			<rtdd>81</rtdd>  
			
			<d>North West Bound</d>
			<dd>Westbound</dd> 
			<dn>NW</dn> 
			<lat>41.9699735874083</lat>
			<lon>-87.76125019352611</lon>
			<pid>16551</pid>
			<pd>Westbound</pd> 
			<pdRtpiFeedName></pdRtpiFeedName>
			<run>F121</run>
			<fs>Jefferson Park Blue Line</fs>
			<op>65929</op>
			<dip>37448</dip>
			<bid>941</bid>				
			<wid1>0F</wid1>
			<wid2>121</wid2>            	
		</bus>



	</buses>
